{
    "birth_geo_city": "",
    "birth_geo_country_long": "United States",
    "birth_geo_country_short": "US",
    "birth_geo_county": "",
    "birth_geo_formatted_address": "New Hampshire, USA",
    "birth_geo_lat": 43.1938516,
    "birth_geo_lng": -71.5723953,
    "birth_geo_neighborhood": "",
    "birth_geo_state_long": "New Hampshire",
    "birth_geo_state_short": "NH",
    "birth_geo_street_name_long": "",
    "birth_geo_street_name_short": "",
    "birth_geo_street_number": "",
    "birth_geo_zip": "",
    "birth_place_geocode_input": "New Hampshire  England"
}